{
  "error": "1",
  "message": "Loading Success!",
  "data": [
    {
      "post_id": "175",
      "post_thumb": "https://raw.githubusercontent.com/Escape02/Videos/master/Theme%20One/1602325118.png",
      "back_image": "https://raw.githubusercontent.com/Escape02/Videos/master/Theme%20One/1602325118.png",
      "ratio": "3:4",
      "cat_id": "15",
      "sticker_info": [
        {
          "st_image": "https://raw.githubusercontent.com/Escape02/Videos/master/Theme%20One/5582_10-10-2020__1602325118.png",
          "sticker_id": "1",
          "st_x_pos": "10",
          "st_y_pos": "10",
          "st_width": "1080",
          "st_height": "1350",
          "st_rotation": "0",
          "st_order": "1"
        },
        {
          "st_image": "https://raw.githubusercontent.com/Escape02/Videos/master/Theme%20One/4132_10-10-2020__1602325118.png",
          "sticker_id": "2",
          "st_x_pos": "74",
          "st_y_pos": "50",
          "st_width": "940",
          "st_height": "1250",
          "st_rotation": "0",
          "st_order": "2"
        },
        {
          "st_image": "https://raw.githubusercontent.com/Escape02/Videos/master/Theme%20One/3512_10-10-2020__1602325118.png",
          "sticker_id": "3",
          "st_x_pos": "139",
          "st_y_pos": "123",
          "st_width": "800",
          "st_height": "1100",
          "st_rotation": "0",
          "st_order": "3"
        },
        {
          "st_image": "https://raw.githubusercontent.com/Escape02/Videos/master/Theme%20One/3632_10-10-2020__1602325118.png",
          "sticker_id": "4",
          "st_x_pos": "10",
          "st_y_pos": "10",
          "st_width": "1080",
          "st_height": "340",
          "st_rotation": "0",
          "st_order": "4"
        },
        {
          "st_image": "https://raw.githubusercontent.com/Escape02/Videos/master/Theme%20One/8511_10-10-2020__1602325118.png",
          "sticker_id": "5",
          "st_x_pos": "229",
          "st_y_pos": "311",
          "st_width": "561",
          "st_height": "553",
          "st_rotation": "0",
          "st_order": "5"
        },
      ],
      "text_info": [
        {
          "text_id": "1",
          "text": "You are invited to",
          "font_family": "Nexa Regular",
          "font_familyI": "Nexa Regular",
          "txt_color": "#000000",
          "txt_alpha": null,
          "txt_x_pos": "366.01",
          "txt_y_pos": "203.63",
          "txt_width": "349.07",
          "txt_height": "47.74",
          "txt_bg_imag": "",
          "txt_rotation": "0",
          "txt_order": "6"
        },
        {
          "text_id": "2",
          "text": "the BABY  SHOWER of",
          "font_family": "Nexa Regular",
          "font_familyI": "Nexa Regular",
          "txt_color": "#000000",
          "txt_alpha": null,
          "txt_x_pos": "309.9",
          "txt_y_pos": "249.63",
          "txt_width": "459.27",
          "txt_height": "47.74 ",
          "txt_bg_imag": "",
          "txt_rotation": "0",
          "txt_order": "7"
        },
        {
          "text_id": "3",
          "text": "August 16,2021",
          "font_family": "Nexa Regular",
          "font_familyI": "Nexa Regular",
          "txt_color": "#000000",
          "txt_alpha": null,
          "txt_x_pos": "383.37",
          "txt_y_pos": "1051.14",
          "txt_width": "313.7",
          "txt_height": "47.75",
          "txt_bg_imag": "",
          "txt_rotation": "0",
          "txt_order": "8"
        },
        {
          "text_id": "4",
          "text": "Sunday | 3:00 pm",
          "font_family": "Nexa Regular",
          "font_familyI": "Nexa Regular",
          "txt_color": "#000000",
          "txt_alpha": null,
          "txt_x_pos": "363.14",
          "txt_y_pos": "1118.87",
          "txt_width": "356.03",
          "txt_height": "47.75",
          "txt_bg_imag": "",
          "txt_rotation": "0",
          "txt_order": "9"
        },
        {
          "text_id": "5",
          "text": "James Mary",
          "font_family": "Boank Regular",
          "font_familyI": "Boank Regular",
          "txt_color": "#2f809a",
          "txt_alpha": null,
          "txt_x_pos": "240.37",
          "txt_y_pos": "846.83",
          "txt_width": "597.2",
          "txt_height": "173.97",
          "txt_bg_imag": "",
          "txt_rotation": "0",
          "txt_order": "10"
        }
      ]
    }
  ]
}